Devil/__init__.py
DevilFree-6.0.dist-info/METADATA
DevilFree-6.0.dist-info/WHEEL
DevilFree-6.0.dist-info/top_level.txt
DevilFree-6.0.dist-info/RECORD
