Metadata-Version: 2.1
Name: DevilFree
Version: 6.0
Summary: A powerful encryption libraries in Python created by the @NasrPy
Author: DevilFree
Classifier: Programming Language :: Python :: 3
